LICENSE
README.md
setup.py
radiojavanapi/__init__.py
radiojavanapi/constants.py
radiojavanapi/exceptions.py
radiojavanapi/extractors.py
radiojavanapi/helper.py
radiojavanapi/models.py
radiojavanapi.egg-info/PKG-INFO
radiojavanapi.egg-info/SOURCES.txt
radiojavanapi.egg-info/dependency_links.txt
radiojavanapi.egg-info/requires.txt
radiojavanapi.egg-info/top_level.txt
radiojavanapi/mixins/__init__.py
radiojavanapi/mixins/account.py
radiojavanapi/mixins/album.py
radiojavanapi/mixins/artist.py
radiojavanapi/mixins/auth.py
radiojavanapi/mixins/browse.py
radiojavanapi/mixins/playlist.py
radiojavanapi/mixins/podcast.py
radiojavanapi/mixins/private.py
radiojavanapi/mixins/search.py
radiojavanapi/mixins/song.py
radiojavanapi/mixins/story.py
radiojavanapi/mixins/user.py
radiojavanapi/mixins/video.py