Metadata-Version: 2.1
Name: radiojavanapi
Version: 0.6.1
Summary: Fast and effective RadioJavan API Wrapper
Home-page: https://github.com/xHossein/radiojavanapi
Author: xHossein
License: MIT
Keywords: radiojavan private api,radiojavan-private-api,radiojavan api,radiojavan-api,rj api,rj-api,radiojavan,radio javan,radio-javan
Classifier: Development Status :: 5 - Production/Stable
Classifier: Intended Audience :: Developers
Classifier: License :: OSI Approved :: MIT License
Classifier: Topic :: Software Development :: Libraries :: Python Modules
Classifier: Programming Language :: Python :: 3.7
Classifier: Programming Language :: Python :: 3.8
Classifier: Programming Language :: Python :: 3.9
Classifier: Programming Language :: Python :: 3.10
Classifier: Programming Language :: Python :: 3.11
Classifier: Programming Language :: Python :: 3.12
Requires-Python: >=3.7
License-File: LICENSE
Requires-Dist: requests==2.32.5
Requires-Dist: requests-toolbelt==1.0.0
Requires-Dist: PySocks==1.7.1
Requires-Dist: pydantic==2.11.9
